odoo8_addon_l10n_br_sale_stock-8.0.1.0.0.99.dev17-py2.7-nspkg.pth
odoo8_addon_l10n_br_sale_stock-8.0.1.0.0.99.dev17.dist-info/METADATA
odoo8_addon_l10n_br_sale_stock-8.0.1.0.0.99.dev17.dist-info/RECORD
odoo8_addon_l10n_br_sale_stock-8.0.1.0.0.99.dev17.dist-info/WHEEL
odoo8_addon_l10n_br_sale_stock-8.0.1.0.0.99.dev17.dist-info/namespace_packages.txt
odoo8_addon_l10n_br_sale_stock-8.0.1.0.0.99.dev17.dist-info/top_level.txt
odoo_addons/l10n_br_sale_stock/README.rst
odoo_addons/l10n_br_sale_stock/__init__.py
odoo_addons/l10n_br_sale_stock/__openerp__.py
odoo_addons/l10n_br_sale_stock/demo/l10n_br_sale_stock_demo.xml
odoo_addons/l10n_br_sale_stock/i18n/pt_BR.po
odoo_addons/l10n_br_sale_stock/models/__init__.py
odoo_addons/l10n_br_sale_stock/models/procurement.py
odoo_addons/l10n_br_sale_stock/models/sale.py
odoo_addons/l10n_br_sale_stock/models/stock_account.py
odoo_addons/l10n_br_sale_stock/security/ir.model.access.csv
odoo_addons/l10n_br_sale_stock/static/description/icon.png
odoo_addons/l10n_br_sale_stock/test/sale_order_demo.yml
odoo_addons/l10n_br_sale_stock/views/sale_stock_view.xml
